LICENSE
MANIFEST.in
README.rst
setup.py
bootstrap_pagination/__init__.py
bootstrap_pagination/templates/bootstrap_pagination/pager.html
bootstrap_pagination/templates/bootstrap_pagination/pagination.html
bootstrap_pagination/templatetags/__init__.py
bootstrap_pagination/templatetags/bootstrap_pagination.py
django_bootstrap_pagination_vinta.egg-info/PKG-INFO
django_bootstrap_pagination_vinta.egg-info/SOURCES.txt
django_bootstrap_pagination_vinta.egg-info/dependency_links.txt
django_bootstrap_pagination_vinta.egg-info/not-zip-safe
django_bootstrap_pagination_vinta.egg-info/top_level.txt
tests/__init__.py
tests/test_helpers.py
tests/test_pager.py
tests/test_paginate.py
tests/test_settings.py