Metadata-Version: 1.1
Name: django-bootstrap-pagination-vinta
Version: 1.6.1
Summary: Render Django Page objects as Bootstrap 3.x Pagination compatible HTML
Home-page: https://github.com/jmcclell/django-bootstrap-pagination
Author: Jason McClellan
Author-email: jason@jasonmccllelan.net
License: MIT licence, see LICENCE
Keywords: django bootstrap pagination templatetag
Platform: UNKNOWN
Classifier: Development Status :: 4 - Beta
Classifier: Intended Audience :: Developers
Classifier: License :: OSI Approved :: MIT License
Classifier: Framework :: Django
Classifier: Framework :: Django :: 1.4
Classifier: Framework :: Django :: 1.5
Classifier: Framework :: Django :: 1.6
Classifier: Framework :: Django :: 1.7
Classifier: Framework :: Django :: 1.8
Classifier: Framework :: Django :: 1.9
Classifier: Programming Language :: Python :: 2.6
Classifier: Programming Language :: Python :: 2.7
Classifier: Programming Language :: Python :: 3.2
Classifier: Programming Language :: Python :: 3.3
Classifier: Programming Language :: Python :: 3.4
Classifier: Programming Language :: Python :: 3.5
